narrative_mapper/__init__.py
narrative_mapper/narrative_analyzer/__init__.py
narrative_mapper/narrative_analyzer/clustering.py
narrative_mapper/narrative_analyzer/embeddings.py
narrative_mapper/narrative_analyzer/formatters.py
narrative_mapper/narrative_analyzer/narrative_mapper.py
narrative_mapper/narrative_analyzer/summarize.py
narrative_mapper/narrative_analyzer/utils.py
narrative_mapper/narrative_mapper_cli/__init__.py
narrative_mapper/narrative_mapper_cli/cli.py
narrativemapper-0.3.4.dist-info/licenses/LICENSE
narrativemapper-0.3.4.dist-info/METADATA
narrativemapper-0.3.4.dist-info/WHEEL
narrativemapper-0.3.4.dist-info/entry_points.txt
narrativemapper-0.3.4.dist-info/top_level.txt
narrativemapper-0.3.4.dist-info/RECORD
