Metadata-Version: 2.4
Name: NarrativeMapper
Version: 0.3.4
Summary: NarrativeMapper is a text analysis pipeline that uncovers the dominant narratives and emotional tones within online communities.
Author-email: jontom01 <jonnyy.thompson@gmail.com>
License: Apache-2.0
Requires-Python: >=3.8
License-File: LICENSE
Requires-Dist: pandas
Requires-Dist: numpy
Requires-Dist: openai
Requires-Dist: umap-learn
Requires-Dist: hdbscan
Requires-Dist: scikit-learn
Requires-Dist: python-dotenv
Requires-Dist: transformers
Requires-Dist: tiktoken
Requires-Dist: rich
Requires-Dist: torch
Dynamic: license-file
